[
  {
    "type": "events",
    "id": "288203",
    "attributes": {
      "repeat_id": null,
      "resource_id": 25,
      "resource_area_id": 35,
      "desc": "Bret Hart Middle School (25)",
      "event_type_id": "20",
      "sub_type": "regular",
      "start": "2026-04-01T10:30:00",
      "start_gmt": "2026-04-01T17:30:00",
      "end": "2026-04-01T12:30:00",
      "end_gmt": "2026-04-01T19:30:00",
      "customer_id": 285574,
      "hteam_id": null,
      "vteam_id": null,
      "league_id": null,
      "home_score": null,
      "visiting_score": null,
      "publish": false,
      "outcome": "",
      "register_capacity": 0,
      "create_u": "egarcia",
      "created_user_type": "SIT_Employee",
      "create_d": "2026-03-03T09:35:20",
      "mod_u": "egarcia",
      "last_modified_user_type": "SIT_Employee",
      "mod_d": "2026-03-03T09:35:20",
      "is_overtime": false,
      "booking_id": 5383,
      "description": null,
      "notice": null,
      "last_resource_id": null,
      "parent_event_id": null,
      "has_gender_locker_rooms": 0,
      "locker_room_type": null,
      "includes_setup_time": false,
      "includes_takedown_time": false,
      "start_date": "2026-04-01T00:00:00",
      "event_start_time": "10:30:00",
      "best_description": null
    }
  },
  {
    "type": "events",
    "id": "266727",
    "attributes": {
      "repeat_id": 266726,
      "resource_id": 25,
      "resource_area_id": 34,
      "desc": "Class: ARISE Spring Enrichment Program 2026",
      "event_type_id": "c",
      "sub_type": "regular",
      "start": "2026-04-01T13:00:00",
      "start_gmt": "2026-04-01T20:00:00",
      "end": "2026-04-01T14:00:00",
      "end_gmt": "2026-04-01T21:00:00",
      "customer_id": 0,
      "hteam_id": 9520,
      "vteam_id": null,
      "league_id": 4142,
      "home_score": null,
      "visiting_score": null,
      "publish": true,
      "outcome": "",
      "register_capacity": 0,
      "create_u": "ssimon",
      "created_user_type": "SIT_Employee",
      "create_d": "2025-12-03T15:32:54",
      "mod_u": "ssimon",
      "last_modified_user_type": "SIT_Employee",
      "mod_d": "2025-12-03T15:32:54",
      "is_overtime": false,
      "booking_id": null,
      "description": null,
      "notice": null,
      "last_resource_id": null,
      "parent_event_id": null,
      "has_gender_locker_rooms": 0,
      "locker_room_type": null,
      "includes_setup_time": false,
      "includes_takedown_time": false,
      "start_date": "2026-04-01T00:00:00",
      "event_start_time": "13:00:00",
      "best_description": null
    }
  },
  {
    "type": "events",
    "id": "281597",
    "attributes": {
      "repeat_id": null,
      "resource_id": 24,
      "resource_area_id": 0,
      "desc": "Class: OIC - Bay Area Bears 10U Evaluation 2026",
      "event_type_id": "c",
      "sub_type": "regular",
      "start": "2026-04-01T17:30:00",
      "start_gmt": "2026-04-02T00:30:00",
      "end": "2026-04-01T18:30:00",
      "end_gmt": "2026-04-02T01:30:00",
      "customer_id": 0,
      "hteam_id": 9786,
      "vteam_id": null,
      "league_id": 4317,
      "home_score": null,
      "visiting_score": null,
      "publish": true,
      "outcome": "",
      "register_capacity": 0,
      "create_u": "bmartin",
      "created_user_type": "SIT_Employee",
      "create_d": "2026-02-06T10:18:11",
      "mod_u": "bmartin",
      "last_modified_user_type": "SIT_Employee",
      "mod_d": "2026-02-06T10:18:11",
      "is_overtime": false,
      "booking_id": null,
      "description": null,
      "notice": null,
      "last_resource_id": null,
      "parent_event_id": null,
      "has_gender_locker_rooms": 0,
      "locker_room_type": null,
      "includes_setup_time": false,
      "includes_takedown_time": false,
      "start_date": "2026-04-01T00:00:00",
      "event_start_time": "17:30:00",
      "best_description": "<p>Bay Area Bears 10U Spring Evaluation&nbsp;</p>"
    }
  },
  {
    "type": "events",
    "id": "281599",
    "attributes": {
      "repeat_id": null,
      "resource_id": 24,
      "resource_area_id": 0,
      "desc": "Class: OIC - Bay Area Bears 12U Evaluation 2026",
      "event_type_id": "c",
      "sub_type": "regular",
      "start": "2026-04-01T18:45:00",
      "start_gmt": "2026-04-02T01:45:00",
      "end": "2026-04-01T19:45:00",
      "end_gmt": "2026-04-02T02:45:00",
      "customer_id": 0,
      "hteam_id": 9787,
      "vteam_id": null,
      "league_id": 4318,
      "home_score": null,
      "visiting_score": null,
      "publish": true,
      "outcome": "",
      "register_capacity": 0,
      "create_u": "bmartin",
      "created_user_type": "SIT_Employee",
      "create_d": "2026-02-06T10:18:37",
      "mod_u": "bmartin",
      "last_modified_user_type": "SIT_Employee",
      "mod_d": "2026-02-06T10:18:37",
      "is_overtime": false,
      "booking_id": null,
      "description": null,
      "notice": null,
      "last_resource_id": null,
      "parent_event_id": null,
      "has_gender_locker_rooms": 0,
      "locker_room_type": null,
      "includes_setup_time": false,
      "includes_takedown_time": false,
      "start_date": "2026-04-01T00:00:00",
      "event_start_time": "18:45:00",
      "best_description": "<p>Bay Area Bears 12U Spring Evaluation&nbsp;</p>"
    }
  },
  {
    "type": "events",
    "id": "281601",
    "attributes": {
      "repeat_id": null,
      "resource_id": 24,
      "resource_area_id": 0,
      "desc": "Class: OIC - Bay Area Bears 14U Evaluation 2026",
      "event_type_id": "c",
      "sub_type": "regular",
      "start": "2026-04-01T20:00:00",
      "start_gmt": "2026-04-02T03:00:00",
      "end": "2026-04-01T21:00:00",
      "end_gmt": "2026-04-02T04:00:00",
      "customer_id": 0,
      "hteam_id": 9788,
      "vteam_id": null,
      "league_id": 4319,
      "home_score": null,
      "visiting_score": null,
      "publish": true,
      "outcome": "",
      "register_capacity": 0,
      "create_u": "bmartin",
      "created_user_type": "SIT_Employee",
      "create_d": "2026-02-06T10:19:15",
      "mod_u": "bmartin",
      "last_modified_user_type": "SIT_Employee",
      "mod_d": "2026-02-06T10:19:15",
      "is_overtime": false,
      "booking_id": null,
      "description": null,
      "notice": null,
      "last_resource_id": null,
      "parent_event_id": null,
      "has_gender_locker_rooms": 0,
      "locker_room_type": null,
      "includes_setup_time": false,
      "includes_takedown_time": false,
      "start_date": "2026-04-01T00:00:00",
      "event_start_time": "20:00:00",
      "best_description": "<p>Bay Area Bears 14U Spring Evaluation&nbsp;</p>"
    }
  }
]